{"format_version":"1.10.0","animation_controllers":{"controller.animation.frog.eat_mob":{"initial_state":"default","states":{"default":{"transitions":[{"eating":"query.is_eating_mob"}]},"eating":{"animations":["tongue"],"transitions":[{"default":"!query.is_eating_mob"}]}}},"controller.animation.frog.croaking":{"initial_state":"default","states":{"default":{"transitions":[{"croaking":"query.is_croaking"}]},"croaking":{"animations":["croak"],"transitions":[{"default":"!query.is_croaking || query.is_eating_mob"}]}}},"controller.animation.frog.updated_general":{"initial_state":"on_land","states":{"on_land":{"animations":[{"walking":"q.modified_move_speed *1.5"},"idle"],"transitions":[{"swimming":"query.is_in_water"},{"jumping":"query.is_jump_goal_jumping"},{"death":"!q.is_alive"},{"eating":"query.is_eating_mob"},{"croaking":"query.is_croaking"}],"blend_transition":0.2,"blend_via_shortest_path":true},"jumping":{"animations":[{"jumping":"query.is_jump_goal_jumping"},"idle",{"walking":"q.modified_move_speed"}],"transitions":[{"on_land":"!query.is_in_water && q.is_on_ground"},{"swimming":"query.is_in_water"},{"death":"!q.is_alive"},{"eating":"query.is_eating_mob"},{"croaking":"query.is_croaking"}],"blend_transition":0.2,"blend_via_shortest_path":true},"swimming":{"animations":[{"swimming":"q.modified_move_speed *1.5"},"idle_water"],"transitions":[{"on_land":"!query.is_in_water"},{"death":"!q.is_alive"},{"eating":"query.is_eating_mob"},{"croaking":"query.is_croaking"}],"blend_transition":0.2,"blend_via_shortest_path":true},"eating":{"animations":["tongue"],"transitions":[{"on_land":"query.any_animation_finished && !q.is_in_water"},{"death":"!q.is_alive"},{"croaking":"query.is_croaking"},{"swimming":"q.any_animation_finished && q.is_in_water"}],"blend_transition":0.2,"blend_via_shortest_path":true},"death":{"animations":["death","death_rotation"],"blend_transition":0.2,"blend_via_shortest_path":true},"croaking":{"animations":["croaking"],"transitions":[{"on_land":"q.any_animation_finished && !q.is_in_water"},{"swimming":"q.any_animation_finished && q.is_in_water"},{"death":"!q.is_alive"}],"blend_transition":0.2,"blend_via_shortest_path":true}}}}}