{"format_version":"1.19.0","animation_controllers":{"controller.animation.strider.move":{"initial_state":"idle","states":{"idle":{"animations":[{"idle":"q.is_alive"},{"look_at_target":"q.is_alive"}],"transitions":[{"walking":"q.ground_speed > 0.5"}],"blend_transition":0.2,"blend_via_shortest_path":true},"walking":{"animations":[{"walking":"q.is_alive"},{"look_at_target":"q.is_alive"}],"transitions":[{"idle":"q.ground_speed < 0.05"}],"blend_transition":0.2,"blend_via_shortest_path":true}}},"controller.animation.strider.death":{"states":{"default":{"transitions":[{"death":"!q.is_alive"}]},"death":{"animations":["death","death_rotation"]}}},"controller.animation.strider.shake":{"states":{"default":{"animations":[{"shake":"q.is_alive"}]}}}}}