{
    "format_version": "1.13.0",
    "minecraft:feature_rules": {
        "description": {
            "identifier": "5fs_br:weighted_decoration_feature",
            "places_feature": "5fs_br:roofed_forest/weighted_decoration_feature"
        },
        "conditions": {
            "placement_pass": "after_surface_pass",
            "minecraft:biome_filter": {
                "test": "has_biome_tag",
                "operator": "==",
                "value": "roofed"
            }
        },
        "distribution": {
            "iterations": 1,
            "scatter_chance": {
                "numerator": 1,
                "denominator": 8
            },
            "x": {
                "distribution": "uniform",
                "extent": [
                    1,
                    15
                ]
            },
            "y": "q.heightmap(v.worldx, v.worldz)",
            "z": {
                "distribution": "uniform",
                "extent": [
                    1,
                    15
                ]
            }
        }
    }
}